MANIFEST.in
README.rst
setup.cfg
setup.py
docs/HISTORY.txt
src/templer/__init__.py
src/templer.dexterity.egg-info/PKG-INFO
src/templer.dexterity.egg-info/SOURCES.txt
src/templer.dexterity.egg-info/dependency_links.txt
src/templer.dexterity.egg-info/entry_points.txt
src/templer.dexterity.egg-info/namespace_packages.txt
src/templer.dexterity.egg-info/not-zip-safe
src/templer.dexterity.egg-info/requires.txt
src/templer.dexterity.egg-info/top_level.txt
src/templer/dexterity/TODO.txt
src/templer/dexterity/__init__.py
src/templer/dexterity/dexterity.py
src/templer/dexterity/localcommands/__init__.py
src/templer/dexterity/localcommands/dexterity.py
src/templer/dexterity/localcommands/templates/dexterity/behavior/+behavior_filename+.py_tmpl
src/templer/dexterity/localcommands/templates/dexterity/behavior/configure.zcml_insert
src/templer/dexterity/localcommands/templates/dexterity/content/+content_class_filename+.py_tmpl
src/templer/dexterity/localcommands/templates/dexterity/content/+contenttype_classname+.txt_tmpl
src/templer/dexterity/localcommands/templates/dexterity/content/tests.py_insert
src/templer/dexterity/localcommands/templates/dexterity/content/+content_class_filename+_templates/sampleview.pt_tmpl
src/templer/dexterity/localcommands/templates/dexterity/content/models/+content_class_filename+.xml
src/templer/dexterity/localcommands/templates/dexterity/content/profiles/default/types.xml_insert
src/templer/dexterity/localcommands/templates/dexterity/content/profiles/default/types/+types_xml_filename+.xml_tmpl
src/templer/dexterity/templates/dexterity/DEXTERITY_README.rst_tmpl
src/templer/dexterity/templates/dexterity/buildout.cfg_tmpl
src/templer/dexterity/templates/dexterity/setup.cfg
src/templer/dexterity/templates/dexterity/setup.py_tmpl
src/templer/dexterity/templates/dexterity/src/+namespace_package+/+package+/INTEGRATION.txt
src/templer/dexterity/templates/dexterity/src/+namespace_package+/+package+/__init__.py_tmpl
src/templer/dexterity/templates/dexterity/src/+namespace_package+/+package+/configure.zcml_tmpl
src/templer/dexterity/templates/dexterity/src/+namespace_package+/+package+/locales/README.txt
src/templer/dexterity/templates/dexterity/src/+namespace_package+/+package+/profiles/default/metadata.xml_tmpl
src/templer/dexterity/templates/dexterity/src/+namespace_package+/+package+/profiles/default/types.xml
